pyshellwrapper/__init__.py
pyshellwrapper/defs.py
pyshellwrapper/parser.py
pyshellwrapper/utils.py
pyshellwrapper/wrapper.py
pyshellwrapper/blueprint/__init__.py
pyshellwrapper/blueprint/compress_libs.json
pyshellwrapper/blueprint/convert.json
pyshellwrapper/blueprint/wget.json
pyshellwrapper-0.4.1.dist-info/LICENSE
pyshellwrapper-0.4.1.dist-info/METADATA
pyshellwrapper-0.4.1.dist-info/WHEEL
pyshellwrapper-0.4.1.dist-info/top_level.txt
pyshellwrapper-0.4.1.dist-info/RECORD
