Metadata-Version: 2.1
Name: pyshellwrapper
Version: 0.4.1
Summary: Working with shell programs in Python made easier.
Home-page: UNKNOWN
Author: Matěj Mitaš
Author-email: contact@matejmitas.com
License: MIT
Platform: UNKNOWN
Requires-Dist: jsonschema (>=3)
Requires-Dist: importlib-resources ; python_version < "3.7"
